CHANGES.txt
COPYRIGHT.txt
LICENSE.txt
README.txt
setup.cfg
setup.py
repoze/__init__.py
repoze.bfg.chameleon_genshi.egg-info/PKG-INFO
repoze.bfg.chameleon_genshi.egg-info/SOURCES.txt
repoze.bfg.chameleon_genshi.egg-info/dependency_links.txt
repoze.bfg.chameleon_genshi.egg-info/entry_points.txt
repoze.bfg.chameleon_genshi.egg-info/namespace_packages.txt
repoze.bfg.chameleon_genshi.egg-info/not-zip-safe
repoze.bfg.chameleon_genshi.egg-info/requires.txt
repoze.bfg.chameleon_genshi.egg-info/top_level.txt
repoze/bfg/__init__.py
repoze/bfg/chameleon_genshi/__init__.py
repoze/bfg/chameleon_genshi/configure.zcml
repoze/bfg/chameleon_genshi/tests/__init__.py
repoze/bfg/chameleon_genshi/tests/test_chameleon_genshi.py
repoze/bfg/chameleon_genshi/tests/fixtures/minimal.genshi