Metadata-Version: 1.0
Name: repoze.bfg.chameleon-genshi
Version: 0.2
Summary: chameleon.genshi template bindings for the repoze.bfg web framework
Home-page: http://bfg.repoze.org
Author: Agendaless Consulting
Author-email: repoze-dev@lists.repoze.org
License: BSD-derived (http://www.repoze.org/LICENSE.txt)
Keywords: bfg repoze.bfg genshi chameleon templates
Platform: UNKNOWN
Classifier: Intended Audience :: Developers
Classifier: Programming Language :: Python
Classifier: Topic :: Internet :: WWW/HTTP :: Dynamic Content
